{
  "$schema": "https://raw.githubusercontent.com/libretiny-eu/libretiny/master/boards/_base/_base.schema.json",
  "_base": ["generic", "silabs-efm32gg11", "ic/efm32gg11b820-qfn64"],
  "build": {
    "mcu": "efm32gg11",
    "variant": "wgm160p-juicebox-40"
  },
  "name": "Enel X JuiceBox 40 (WGM160P host)",
  "url": "https://www.silabs.com/wireless/wi-fi/wgm160-series-wi-fi-modules",
  "vendor": "Silicon Labs",
  "pcb": {
    "symbol": "WGM160P JuiceBox 40",
    "pinout": {
      "PB5":  { "GPIO": "PB5",  "ARD": "LED0",   "PHYSICAL": "RGB LED red, active-high (bench-verified 2026-06-11, each pin driven alone via SWD)" },
      "PB6":  { "GPIO": "PB6",  "ARD": "LED1",   "PHYSICAL": "RGB LED green, active-high (bench-verified 2026-06-11, each pin driven alone via SWD)" },
      "PD8":  { "GPIO": "PD8",  "ARD": "LED2",   "PHYSICAL": "RGB LED blue, active-high (bench-verified 2026-06-11; SWD sweep find, not in Gecko OS map)" },
      "PC4":  { "GPIO": "PC4",  "ARD": "BTN0",   "PHYSICAL": "factory_reset line (Gecko GPIO 16; SPI16 CS)" },
      "PE6":  { "GPIO": "PE6",  "ARD": "RX",     "PHYSICAL": "console UART RX, module pin 47 (USART0 LOC1)" },
      "PE7":  { "GPIO": "PE7",  "ARD": "TX",     "PHYSICAL": "console UART TX, module pin 46 (USART0 LOC1)" },
      "PB3":  { "GPIO": "PB3",  "PHYSICAL": "no visible function (Gecko OS table said RGB; drives nothing — bench-verified 2026-06-11)" },
      "PB13": { "GPIO": "PB13", "PHYSICAL": "HFXO_P (50 MHz crystal)" },
      "PB14": { "GPIO": "PB14", "PHYSICAL": "HFXO_N (50 MHz crystal)" }
    },
    "blacklist": {
      "PE8":  "Internal WGM160P SiP: WF200 SDIO DAT3 (LOC0)",
      "PE9":  "Internal WGM160P SiP: WF200 SDIO DAT2 / HIF_SEL (LOC0; level at RESETn rising selects bus: high=SDIO, low=SPI)",
      "PE10": "Internal WGM160P SiP: WF200 SDIO DAT1 (LOC0)",
      "PE11": "Internal WGM160P SiP: WF200 SDIO DAT0 (LOC0)",
      "PE12": "Internal WGM160P SiP: WF200 SDIO CMD (LOC0)",
      "PE13": "Internal WGM160P SiP: WF200 SDIO CLK (LOC0)",
      "PA8":  "Internal WGM160P SiP: WF200 WIRQ",
      "PA12": "Internal WGM160P SiP: WF200 LP_CLK",
      "PE4":  "Internal WGM160P SiP: WF200 WUP",
      "PF12": "Internal WGM160P SiP: WF200 RESET (active-low)"
    }
  }
}
